webos_emulator/__init__.py
webos_emulator/__main__.py
webos_emulator/check.py
webos_emulator/cli.py
webos_emulator/exceptions.py
webos_emulator/version.py
webos_emulator/webos-emulator.json
webos_emulator/webos_emulator.py
webos_emulator-0.9.5.dist-info/AUTHORS.rst
webos_emulator-0.9.5.dist-info/LICENSE
webos_emulator-0.9.5.dist-info/METADATA
webos_emulator-0.9.5.dist-info/WHEEL
webos_emulator-0.9.5.dist-info/entry_points.txt
webos_emulator-0.9.5.dist-info/top_level.txt
webos_emulator-0.9.5.dist-info/RECORD
