Metadata-Version: 2.1
Name: webos-emulator
Version: 0.9.5
Summary: webOS Emulator Launcher
Home-page: https://github.com/webosose/webos-emulator
Author: Heegoo Han
Author-email: heegoo.han@lge.com
License: MIT license
Keywords: webos-emulator
Classifier: Development Status :: 2 - Pre-Alpha
Classifier: Intended Audience :: Developers
Classifier: License :: OSI Approved :: MIT License
Classifier: Natural Language :: English
Classifier: Programming Language :: Python :: 3
Classifier: Programming Language :: Python :: 3.6
Classifier: Programming Language :: Python :: 3.7
Classifier: Programming Language :: Python :: 3.8
Requires-Python: >=3.6
License-File: LICENSE
License-File: AUTHORS.rst
